ai_dbug/__init__.py
ai_dbug/analyzer.py
ai_dbug/core.py
ai_dbug/formatter.py
ai_dbug/knowledge_base.py
ai_dbug-0.1.0.dist-info/licenses/LICENSE
ai_dbug-0.1.0.dist-info/METADATA
ai_dbug-0.1.0.dist-info/WHEEL
ai_dbug-0.1.0.dist-info/top_level.txt
ai_dbug-0.1.0.dist-info/RECORD
