Metadata-Version: 2.4
Name: ai-dbug
Version: 0.1.0
Summary: AI-powered Python debugger that explains errors in plain English with practical fixes
Home-page: https://github.com/jithubaiju55/ai-dbug
Author: Jithu Baiju
Author-email: Jithu Baiju <jithubaiju124@gmail.com>
Maintainer-email: Jithu Baiju <jithubaiju124@gmail.com>
License: MIT
Project-URL: Homepage, https://github.com/jithubaiju55/ai-dbug
Project-URL: Documentation, https://github.com/jithubaiju55/ai-dbug#readme
Project-URL: Repository, https://github.com/jithubaiju55/ai-dbug
Project-URL: Bug Tracker, https://github.com/jithubaiju55/ai-dbug/issues
Project-URL: Changelog, https://github.com/jithubaiju55/ai-dbug/blob/main/CHANGELOG.md
Keywords: debugging,errors,ai,developer-tools,traceback,error-handling,python-debugger,error-explanation,beginner-friendly
Classifier: Development Status :: 4 - Beta
Classifier: Intended Audience :: Developers
Classifier: Intended Audience :: Education
Classifier: License :: OSI Approved :: MIT License
Classifier: Operating System :: OS Independent
Classifier: Programming Language :: Python :: 3
Classifier: Programming Language :: Python :: 3.7
Classifier: Programming Language :: Python :: 3.8
Classifier: Programming Language :: Python :: 3.9
Classifier: Programming Language :: Python :: 3.10
Classifier: Programming Language :: Python :: 3.11
Classifier: Programming Language :: Python :: 3.12
Classifier: Topic :: Software Development :: Debuggers
Classifier: Topic :: Software Development :: Libraries :: Python Modules
Classifier: Topic :: Education
Classifier: Topic :: Utilities
Requires-Python: >=3.7
License-File: LICENSE
Provides-Extra: color
Requires-Dist: rich>=10.0.0; extra == "color"
Provides-Extra: full
Requires-Dist: rich>=10.0.0; extra == "full"
Requires-Dist: colorama>=0.4.4; extra == "full"
Provides-Extra: dev
Requires-Dist: pytest>=7.0.0; extra == "dev"
Requires-Dist: pytest-cov>=4.0.0; extra == "dev"
Requires-Dist: black>=22.0.0; extra == "dev"
Requires-Dist: flake8>=5.0.0; extra == "dev"
Requires-Dist: mypy>=0.990; extra == "dev"
Requires-Dist: build>=0.10.0; extra == "dev"
Requires-Dist: twine>=4.0.0; extra == "dev"
Dynamic: author
Dynamic: home-page
Dynamic: license-file
Dynamic: requires-python
